sic2dc/__init__.py
sic2dc/sic2dc_cli.py
sic2dc/src/__init__.py
sic2dc/src/base_cures.py
sic2dc/src/base_dump.py
sic2dc/src/base_filters.py
sic2dc/src/config_compare.py
sic2dc/src/schema.py
sic2dc/src/tmp_ts.py
sic2dc/src/tools.py
sic2dc/tests/__init__.py
sic2dc/tests/conftest.py
sic2dc/tests/test_ccbase.py
sic2dc/tests/test_key_nokey.py
sic2dc/tests/test_tools.py
sic2dc-0.0.11.dist-info/LICENSE
sic2dc-0.0.11.dist-info/METADATA
sic2dc-0.0.11.dist-info/WHEEL
sic2dc-0.0.11.dist-info/entry_points.txt
sic2dc-0.0.11.dist-info/top_level.txt
sic2dc-0.0.11.dist-info/RECORD
