Metadata-Version: 2.2
Name: sic2dc
Version: 0.0.11
Summary: Simple indented config to dict compare.
Author-email: Alexander Onishchenko <alexonishchenko@gmail.com>
License: MIT License
Project-URL: repository, https://github.com/alexonishchenko/sic2dc
Project-URL: homepage, https://github.com/alexonishchenko/sic2dc
Keywords: configuration,difference,diff,compare,config-compare,network,network-config
Requires-Python: >=3.11
License-File: LICENSE
Requires-Dist: pydantic
Requires-Dist: pydantic_core
Requires-Dist: ruamel.yaml
Requires-Dist: ruamel.yaml.clib
Provides-Extra: dev
Requires-Dist: iniconfig; extra == "dev"
Requires-Dist: packaging; extra == "dev"
Requires-Dist: pluggy; extra == "dev"
Requires-Dist: pytest; extra == "dev"
Requires-Dist: black; extra == "dev"
Requires-Dist: click; extra == "dev"
Requires-Dist: mypy-extensions; extra == "dev"
Requires-Dist: pathspec; extra == "dev"
Requires-Dist: platformdirs; extra == "dev"
